{"res/atlas/Game/Skeleton/facedefeated.atlas":["Game/Skeleton/facedefeated/",["emoji_02.png"]],"res/atlas/Game/Skeleton/facevictory.atlas":["Game/Skeleton/facevictory/",["emoji_01.png"]],"res/atlas/Game/Skeleton/GetNew.atlas":["Game/Skeleton/GetNew/",["getnew.png"]],"res/atlas/Game/Skeleton/Resurgence.atlas":["Game/Skeleton/Resurgence/",["fuhuo.png"]],"res/atlas/Game/UI/SkinIcon.atlas":["Game/UI/SkinIcon/",["Dress001.png","Dress002.png","Dress003.png","Dress004.png","Dress005.png","Dress006.png","hair001.png","hair002.png","hair003.png","hair004.png","hair005.png","hair006.png","wing00.png","wing01.png","wing02.png","wing03.png","wing04.png"]],"res/atlas/Game/UI.atlas":["Game/UI/",["CursorHand2.png","bg_xinshou.png","glow_02.png","icon_mainui_shengjiicon01.png","icon_mainui_shengjiicon02.png","icon_mainui_shengjiicon03.png","img_2progrems_battle_bar.png","img_2progrems_battle_bg.png","img_7dayjiangli.png","img_beAttack.png","img_bg_choujiang_02.png","img_bg_choujiang_03.png","img_bg_jianglibeishu.png","img_bg_mainui_money_01.png","img_bg_skin_01.png","img_btn_back.png","img_btn_box.png","img_btn_common_01_normal.png","img_btn_common_02_normal.png","img_btn_common_add_normal.png","img_btn_guanbi.png","img_btn_mainui_choujiang_normal.png","img_btn_mainui_gengduohaowan.png","img_btn_mainui_pifu_normal.png","img_btn_mainui_qiandao_normal.png","img_btn_mainui_shengji_normal.png","img_btn_mainui_tianjiazhuomian.png","img_btn_mainui_wujin_normal.png","img_btn_mainui_zhuanpan_normal.png","img_btn_money_add_normal.png","img_btn_shouye.png","img_btn_skin_close_normal.png","img_btn_skintype_press.png","img_btn_tab_1.png","img_btn_tab_2.png","img_btn_zadan_chick_normal.png","img_btn_zadan_chick_press.png","img_btn_zhuanpan_close_normal.png","img_home_btn_putong.png","img_home_btn_wujin.png","img_icon_battle_boss_01.png","img_icon_battlebg_01.png","img_icon_battlebg_02.png","img_icon_chongci_big.png","img_icon_choujiang_best_bg.png","img_icon_choujiang_gift.png","img_icon_common_ad_01.png","img_icon_common_ad_02.png","img_icon_day07.png","img_icon_jianglibeishuzhizhen.png","img_icon_key_01.png","img_icon_key_02.png","img_icon_money_01.png","img_icon_money_01b.png","img_icon_money_02.png","img_icon_qiandao_bg01.png","img_icon_qiandao_bg07.png","img_icon_qiandao_yiqiandao.png","img_icon_share_figer.png","img_icon_skin_choose.png","img_icon_tab_1.png","img_icon_tab_2.png","img_icon_tab_3.png","img_icon_text_benjujiesuan.png","img_icon_text_benpaosudu.png","img_icon_text_chakanguanggao.png","img_icon_text_chongcijuli.png","img_icon_text_choujiangcishu.png","img_icon_text_day1.png","img_icon_text_day2.png","img_icon_text_day3.png","img_icon_text_day4.png","img_icon_text_day5.png","img_icon_text_day6.png","img_icon_text_gongxihuode.png","img_icon_text_gongxitongguan.png","img_icon_text_guankanshipinlingqu20tili.png","img_icon_text_guanqia.png","img_icon_text_jiesuanbeishu.png","img_icon_text_jiesuoxinpifu.png","img_icon_text_jixuyouxi.png","img_icon_text_kaishiyouxi.png","img_icon_text_leijidenglu7tian.png","img_icon_text_lijilingqu.png","img_icon_text_lijiqiandao.png","img_icon_text_lijizhuangban.png","img_icon_text_mianfeichoujiang.png","img_icon_text_mianfeilingqu.png","img_icon_text_qiriqiandaojiangli.png","img_icon_text_shiyongpifu.png","img_icon_text_shuangbeilingqu.png","img_icon_text_shuxingjia1000.png","img_icon_text_tiaoguobenguan.png","img_icon_text_tilibuzu.png","img_icon_text_tongguanshibai.png","img_icon_text_xiacizaishuo.png","img_icon_text_xingyundazhuanpan.png","img_icon_text_zaichou3ci.png","img_icon_text_zailaiyici.png","img_icon_text_zhijielingqu.png","img_icon_text_zuanshibuzu.png","img_icon_text_zuihaodejiangli.png","img_icon_tili_02.png","img_icon_tili_20.png","img_icon_tips_dian.png","img_icon_win_title_a.png","img_icon_win_title_b.png","img_icon_zhuanpan_01.png","img_icon_zhuanpan_02.png","img_icon_zhuanpan_03.png","img_icon_zhuanpan_title_01.png","img_icon_zhuanpan_zailaiyici.png","img_icon_zuanshibig.png","img_progrems_battle_bar.png","img_progrems_battle_bg.png","img_progrems_battle_boss_bar01.png","img_progrems_battle_boss_bar02.png","img_progrems_battle_boss_bg.png","img_progress_01_1(1).png","img_progress_01_2(1).png","img_progress_01_icon.png","img_progress_xuli_1.png","img_progress_xuli_2.png","img_skin_lock.png","img_text_btn_09.png","img_text_btn_icon_jisuchongci.png","img_text_btn_icon_lijijinru.png","img_text_btn_icon_lijishiyong.png","img_text_btn_icon_no.png","img_text_btn_icon_yes.png","img_text_skill_01.png","img_text_skill_02.png","img_text_skill_03.png","img_text_tips_001.png","img_text_tips_01.png","img_tips_effects.png","img_title_gongxi.png","img_title_shibai.png"]]}